<?xml version="1.0" encoding="ISO-8859-1" standalone="no"?><CURRICULO-VITAE SISTEMA-ORIGEM-XML="LATTES_OFFLINE" NUMERO-IDENTIFICADOR="3016248509231033" DATA-ATUALIZACAO="16032022" HORA-ATUALIZACAO="151802"><DADOS-GERAIS NOME-COMPLETO="Pedro Vincius Meerholz" NOME-EM-CITACOES-BIBLIOGRAFICAS="MEERHOLZ, P. V." NACIONALIDADE="B" PAIS-DE-NASCIMENTO="Brasil" UF-NASCIMENTO="" CIDADE-NASCIMENTO="" PERMISSAO-DE-DIVULGACAO="NAO" DATA-FALECIMENTO="" SIGLA-PAIS-NACIONALIDADE="BRA" PAIS-DE-NACIONALIDADE="Brasil" ORCID-ID=""><ENDERECO FLAG-DE-PREFERENCIA="ENDERECO_RESIDENCIAL"><ENDERECO-PROFISSIONAL CODIGO-INSTITUICAO-EMPRESA="" NOME-INSTITUICAO-EMPRESA="" CODIGO-ORGAO="" NOME-ORGAO="" CODIGO-UNIDADE="" NOME-UNIDADE="" LOGRADOURO-COMPLEMENTO="" PAIS="" UF="" CEP="" CIDADE="" BAIRRO="" DDD="" TELEFONE="" RAMAL="" FAX="" CAIXA-POSTAL="" HOME-PAGE=""/></ENDERECO><FORMACAO-ACADEMICA-TITULACAO><GRADUACAO SEQUENCIA-FORMACAO="2" NIVEL="1" TITULO-DO-TRABALHO-DE-CONCLUSAO-DE-CURSO="" NOME-DO-ORIENTADOR="" CODIGO-INSTITUICAO="000200000993" NOME-INSTITUICAO="Faculdade de Tecnologia SENAI Florianpolis (SC)" CODIGO-ORGAO="" NOME-ORGAO="" CODIGO-CURSO="90000000" NOME-CURSO="Anlise e Desenvolvimento de Sistemas" CODIGO-AREA-CURSO="90000000" STATUS-DO-CURSO="EM_ANDAMENTO" ANO-DE-INICIO="2021" ANO-DE-CONCLUSAO="" FLAG-BOLSA="NAO" CODIGO-AGENCIA-FINANCIADORA="" NOME-AGENCIA="" NUMERO-ID-ORIENTADOR="" CODIGO-CURSO-CAPES="" TITULO-DO-TRABALHO-DE-CONCLUSAO-DE-CURSO-INGLES="" NOME-CURSO-INGLES="" FORMACAO-ACADEMICA-TITULACAO="" TIPO-GRADUACAO="N" CODIGO-INSTITUICAO-GRAD="" NOME-INSTITUICAO-GRAD="" CODIGO-INSTITUICAO-OUTRA-GRAD="" NOME-INSTITUICAO-OUTRA-GRAD="" NOME-ORIENTADOR-GRAD=""/><ENSINO-MEDIO-SEGUNDO-GRAU SEQUENCIA-FORMACAO="1" NIVEL="C" CODIGO-INSTITUICAO="000100000991" NOME-INSTITUICAO="Aderbal Ramos da Silva" STATUS-DO-CURSO="CONCLUIDO" ANO-DE-INICIO="2018" ANO-DE-CONCLUSAO="2020"/></FORMACAO-ACADEMICA-TITULACAO><AREAS-DE-ATUACAO><AREA-DE-ATUACAO SEQUENCIA-AREA-DE-ATUACAO="1" NOME-GRANDE-AREA-DO-CONHECIMENTO="CIENCIAS_EXATAS_E_DA_TERRA" NOME-DA-AREA-DO-CONHECIMENTO="Cincia da Computao" NOME-DA-SUB-AREA-DO-CONHECIMENTO="" NOME-DA-ESPECIALIDADE=""/></AREAS-DE-ATUACAO><IDIOMAS><IDIOMA IDIOMA="PT" DESCRICAO-DO-IDIOMA="Portugus" PROFICIENCIA-DE-LEITURA="BEM" PROFICIENCIA-DE-FALA="BEM" PROFICIENCIA-DE-ESCRITA="BEM" PROFICIENCIA-DE-COMPREENSAO="BEM"/><IDIOMA IDIOMA="EN" DESCRICAO-DO-IDIOMA="Ingls" PROFICIENCIA-DE-LEITURA="POUCO" PROFICIENCIA-DE-FALA="POUCO" PROFICIENCIA-DE-ESCRITA="POUCO" PROFICIENCIA-DE-COMPREENSAO="POUCO"/></IDIOMAS></DADOS-GERAIS><PRODUCAO-BIBLIOGRAFICA/><PRODUCAO-TECNICA/><OUTRA-PRODUCAO/><DADOS-COMPLEMENTARES><FORMACAO-COMPLEMENTAR/><INFORMACOES-ADICIONAIS-INSTITUICOES><INFORMACAO-ADICIONAL-INSTITUICAO CODIGO-INSTITUICAO="000100000991" SIGLA-INSTITUICAO="ARS" SIGLA-UF-INSTITUICAO="" SIGLA-PAIS-INSTITUICAO="BRA" NOME-PAIS-INSTITUICAO="Brasil" FLAG-AGENCIA-FOMENTO="NAO" FLAG-INSTITUICAO-DE-ENSINO="NAO"/><INFORMACAO-ADICIONAL-INSTITUICAO CODIGO-INSTITUICAO="000200000993" SIGLA-INSTITUICAO="SENAI" SIGLA-UF-INSTITUICAO="" SIGLA-PAIS-INSTITUICAO="BRA" NOME-PAIS-INSTITUICAO="Brasil" FLAG-AGENCIA-FOMENTO="NAO" FLAG-INSTITUICAO-DE-ENSINO="NAO"/></INFORMACOES-ADICIONAIS-INSTITUICOES><INFORMACOES-ADICIONAIS-CURSOS><INFORMACAO-ADICIONAL-CURSO CODIGO-CURSO="90000000" CODIGO-ORGAO="" NOME-ORGAO="" CODIGO-INSTITUICAO="000200000993" NOME-INSTITUICAO="Faculdade de Tecnologia SENAI Florianpolis (SC)" NOME-GRANDE-AREA-DO-CONHECIMENTO="CIENCIAS_EXATAS_E_DA_TERRA" NOME-DA-AREA-DO-CONHECIMENTO="Cincia da Computao" NOME-DA-SUB-AREA-DO-CONHECIMENTO="" NOME-DA-ESPECIALIDADE="" NIVEL-CURSO="GRADUACAO"/></INFORMACOES-ADICIONAIS-CURSOS></DADOS-COMPLEMENTARES></CURRICULO-VITAE>